crossref_cite/__init__.py
crossref_cite/__main__.py
crossref_cite/cache.py
crossref_cite/client.py
crossref_cite/config.py
crossref_cite/parsers.py
crossref_cite/server.py
crossref_cite_mcp-0.1.2.dist-info/METADATA
crossref_cite_mcp-0.1.2.dist-info/WHEEL
crossref_cite_mcp-0.1.2.dist-info/entry_points.txt
crossref_cite_mcp-0.1.2.dist-info/RECORD
