Metadata-Version: 2.4
Name: crossref-cite-mcp
Version: 0.1.2
Summary: MCP tool for resolving paper citations via Crossref API with multiple format support
Project-URL: Homepage, https://github.com/h-lu/crossref-cite-mcp
Project-URL: Repository, https://github.com/h-lu/crossref-cite-mcp
Project-URL: Issues, https://github.com/h-lu/crossref-cite-mcp/issues
Author-email: Haibo Lu <luhaibo1985@gmail.com>
License-Expression: MIT
Keywords: bibliography,bibtex,citation,crossref,doi,mcp
Classifier: Development Status :: 4 - Beta
Classifier: Intended Audience :: Developers
Classifier: Intended Audience :: Science/Research
Classifier: License :: OSI Approved :: MIT License
Classifier: Programming Language :: Python :: 3
Classifier: Programming Language :: Python :: 3.10
Classifier: Programming Language :: Python :: 3.11
Classifier: Programming Language :: Python :: 3.12
Classifier: Topic :: Scientific/Engineering
Classifier: Topic :: Text Processing :: Markup :: LaTeX
Requires-Python: >=3.10
Requires-Dist: httpx>=0.27.0
Requires-Dist: mcp>=1.0.0
Requires-Dist: pydantic>=2.0.0
Provides-Extra: dev
Requires-Dist: mypy>=1.8.0; extra == 'dev'
Requires-Dist: pytest-asyncio>=0.23.0; extra == 'dev'
Requires-Dist: pytest-cov>=4.0.0; extra == 'dev'
Requires-Dist: pytest-vcr>=1.0.0; extra == 'dev'
Requires-Dist: pytest>=8.0.0; extra == 'dev'
Requires-Dist: ruff>=0.1.0; extra == 'dev'
